headlock/__init__.py
headlock/bridge_gen.py
headlock/c_parser.py
headlock/testsetup.py
headlock/address_space/__init__.py
headlock/address_space/inprocess.py
headlock/address_space/virtual.py
headlock/buildsys_drvs/__init__.py
headlock/buildsys_drvs/default.py
headlock/buildsys_drvs/gcc.py
headlock/buildsys_drvs/mingw.py
headlock/c_data_model/__init__.py
headlock/c_data_model/array.py
headlock/c_data_model/core.py
headlock/c_data_model/enum.py
headlock/c_data_model/float.py
headlock/c_data_model/funcpointer.py
headlock/c_data_model/function.py
headlock/c_data_model/integer.py
headlock/c_data_model/memory_access.py
headlock/c_data_model/pointer.py
headlock/c_data_model/struct.py
headlock/c_data_model/union.py
headlock/c_data_model/vector.py
headlock/c_data_model/void.py
headlock/integrations/pytest/__init__.py
headlock/integrations/pytest/common.py
headlock/integrations/pytest/debug_failed.py
headlock/integrations/pytest/plugin_headlock_debug.py
headlock/integrations/pytest/plugin_headlock_report.py
headlock-0.6.0.dist-info/licenses/LICENSE
headlock-0.6.0.dist-info/METADATA
headlock-0.6.0.dist-info/WHEEL
headlock-0.6.0.dist-info/entry_points.txt
headlock-0.6.0.dist-info/top_level.txt
headlock-0.6.0.dist-info/RECORD
