Metadata-Version: 2.4
Name: headlock
Version: 0.6.0
Summary: An adapter for making C code testable from Python
Home-page: https://headlock.readthedocs.io/en/latest/index.html
Author: Robert Hölzl
Author-email: robert.hoelzl@posteo.de
Classifier: Development Status :: 4 - Beta
Classifier: Operating System :: Microsoft :: Windows
Classifier: Operating System :: POSIX :: Linux
Classifier: Operating System :: MacOS
Classifier: Intended Audience :: Developers
Classifier: License :: OSI Approved :: MIT License
Classifier: Programming Language :: Python :: 3.10
Classifier: Programming Language :: Python :: 3.11
Classifier: Programming Language :: Python :: 3.12
Classifier: Programming Language :: Python :: 3.13
Classifier: Programming Language :: Python :: 3.14
Classifier: Programming Language :: C
Classifier: Topic :: Software Development :: Testing
License-File: LICENSE
Requires-Dist: libclang<19.0.0,>=18.1.1
Dynamic: author
Dynamic: author-email
Dynamic: classifier
Dynamic: description
Dynamic: description-content-type
Dynamic: home-page
Dynamic: license-file
Dynamic: requires-dist
Dynamic: summary
